docs/conf.py
examples/cli_example.py
examples/example_calm/run_populationsim.py
examples/example_calm_repop/run_populationsim.py
examples/example_oceanside_repop/construct_pipe.py
examples/example_oceanside_repop/run_populationsim.py
examples/example_survey_weighting/run_populationsim.py
examples/example_test/convert_test_data.py
examples/example_test/run_populationsim.py
examples/example_test/extensions/__init__.py
populationsim/__init__.py
populationsim/__main__.py
populationsim/run.py
populationsim/balancing/__init__.py
populationsim/balancing/balancers.py
populationsim/balancing/balancers_numba.py
populationsim/balancing/constants.py
populationsim/balancing/simul_balancer.py
populationsim/balancing/single_balancer.py
populationsim/balancing/wrappers.py
populationsim/core/__init__.py
populationsim/core/assign.py
populationsim/core/config.py
populationsim/core/helper.py
populationsim/core/inject.py
populationsim/core/input.py
populationsim/core/mem.py
populationsim/core/memory_sidecar.py
populationsim/core/mp_tasks.py
populationsim/core/pipeline.py
populationsim/core/random.py
populationsim/core/tracing.py
populationsim/core/util.py
populationsim/integerizing/__init__.py
populationsim/integerizing/constants.py
populationsim/integerizing/lp_cvx.py
populationsim/integerizing/lp_ortools.py
populationsim/integerizing/simul_integerizer.py
populationsim/integerizing/single_integerizer.py
populationsim/integerizing/smart_round.py
populationsim/integerizing/wrappers.py
populationsim/steps/__init__.py
populationsim/steps/expand_households.py
populationsim/steps/final_seed_balancing.py
populationsim/steps/initial_seed_balancing.py
populationsim/steps/input_pre_processor.py
populationsim/steps/integerize_final_seed_weights.py
populationsim/steps/meta_control_factoring.py
populationsim/steps/output.py
populationsim/steps/repop_balancing.py
populationsim/steps/setup_data_structures.py
populationsim/steps/sub_balancing.py
populationsim/steps/summarize.py
populationsim-0.10.0.dist-info/licenses/LICENSE.txt
populationsim-0.10.0.dist-info/METADATA
populationsim-0.10.0.dist-info/WHEEL
populationsim-0.10.0.dist-info/entry_points.txt
populationsim-0.10.0.dist-info/top_level.txt
populationsim-0.10.0.dist-info/RECORD
