Metadata-Version: 2.4
Name: populationsim
Version: 0.10.0
Summary: Population Synthesis (for ActivitySim)
Author-email: Ben Stabler <ben.stabler@rsginc.com>
Requires-Python: <3.13,>=3.9
License-File: LICENSE.txt
Requires-Dist: ortools>=5.1.4045
Requires-Dist: pyinstrument>=5.0.1
Requires-Dist: pyyaml>=6.0.2
Requires-Dist: psutil>=7.0.0
Requires-Dist: pandas>=2.2
Requires-Dist: numpy<2,>=1.16.1
Requires-Dist: tables>=3.9
Requires-Dist: orca>=1.8
Requires-Dist: blosc2>=2.5.1
Requires-Dist: cvxpy[glpk]>=1.6.5
Requires-Dist: numba>=0.60.0
Requires-Dist: pyarrow>=20.0.0
Dynamic: license-file
